elefantolib_django/__init__.py
elefantolib_django/middleware.py
elefantolib_django/pagination.py
elefantolib_django/permissions.py
elefantolib_django/serializers/__init__.py
elefantolib_django/serializers/mixins.py
elefantolib_django-0.2.1.dist-info/WHEEL
elefantolib_django-0.2.1.dist-info/METADATA
elefantolib_django-0.2.1.dist-info/RECORD
