Metadata-Version: 2.1
Name: elefantolib-django
Version: 0.2.1
Summary: 
Author: Aibar
Author-email: bekaybar@gmail.com
Requires-Python: >=3.10,<4.0
Classifier: Programming Language :: Python :: 3
Classifier: Programming Language :: Python :: 3.10
Classifier: Programming Language :: Python :: 3.11
Requires-Dist: django (>=4.2.3,<5.0.0)
Requires-Dist: djangorestframework (>=3.14.0,<4.0.0)
Requires-Dist: elefantolib (>=0.12.1,<0.13.0)
